aider/__init__.py
aider/__main__.py
aider/__version__.py
aider/analytics.py
aider/args.py
aider/args_formatter.py
aider/commands.py
aider/diffs.py
aider/dump.py
aider/format_settings.py
aider/gui.py
aider/help.py
aider/help_pats.py
aider/history.py
aider/io.py
aider/linter.py
aider/llm.py
aider/main.py
aider/mdstream.py
aider/models.py
aider/prompts.py
aider/repo.py
aider/repomap.py
aider/report.py
aider/run_cmd.py
aider/scrape.py
aider/sendchat.py
aider/special.py
aider/urls.py
aider/utils.py
aider/versioncheck.py
aider/voice.py
aider/coders/__init__.py
aider/coders/architect_coder.py
aider/coders/architect_prompts.py
aider/coders/ask_coder.py
aider/coders/ask_prompts.py
aider/coders/base_coder.py
aider/coders/base_prompts.py
aider/coders/chat_chunks.py
aider/coders/editblock_coder.py
aider/coders/editblock_fenced_coder.py
aider/coders/editblock_fenced_prompts.py
aider/coders/editblock_func_coder.py
aider/coders/editblock_func_prompts.py
aider/coders/editblock_prompts.py
aider/coders/editor_editblock_coder.py
aider/coders/editor_editblock_prompts.py
aider/coders/editor_whole_coder.py
aider/coders/editor_whole_prompts.py
aider/coders/help_coder.py
aider/coders/help_prompts.py
aider/coders/search_replace.py
aider/coders/single_wholefile_func_coder.py
aider/coders/single_wholefile_func_prompts.py
aider/coders/udiff_coder.py
aider/coders/udiff_prompts.py
aider/coders/wholefile_coder.py
aider/coders/wholefile_func_coder.py
aider/coders/wholefile_func_prompts.py
aider/coders/wholefile_prompts.py
aider/queries/README.md
aider/queries/tree-sitter-c-tags.scm
aider/queries/tree-sitter-c_sharp-tags.scm
aider/queries/tree-sitter-cpp-tags.scm
aider/queries/tree-sitter-elisp-tags.scm
aider/queries/tree-sitter-elixir-tags.scm
aider/queries/tree-sitter-elm-tags.scm
aider/queries/tree-sitter-go-tags.scm
aider/queries/tree-sitter-java-tags.scm
aider/queries/tree-sitter-javascript-tags.scm
aider/queries/tree-sitter-ocaml-tags.scm
aider/queries/tree-sitter-php-tags.scm
realsense_copilot-0.61.1.dev36.dist-info/LICENSE.txt
realsense_copilot-0.61.1.dev36.dist-info/METADATA
realsense_copilot-0.61.1.dev36.dist-info/WHEEL
realsense_copilot-0.61.1.dev36.dist-info/entry_points.txt
realsense_copilot-0.61.1.dev36.dist-info/top_level.txt
realsense_copilot-0.61.1.dev36.dist-info/RECORD
